nexora/__init__.py
nexora/api.py
nexora/autotuna.py
nexora/boruta.py
nexora/enums.py
nexora/logger.py
nexora/metrics.py
nexora/params.py
nexora/predict.py
nexora/schemas.py
nexora/utils.py
nexora/cli/__init__.py
nexora/cli/autotuna.py
nexora/cli/explain.py
nexora/cli/monitor.py
nexora/cli/predict.py
nexora/cli/serve.py
nexora/cli/train.py
nexora-0.1.0.dist-info/LICENSE
nexora-0.1.0.dist-info/METADATA
nexora-0.1.0.dist-info/WHEEL
nexora-0.1.0.dist-info/entry_points.txt
nexora-0.1.0.dist-info/top_level.txt
nexora-0.1.0.dist-info/RECORD
