Metadata-Version: 2.1
Name: nexora
Version: 0.1.0
Summary: This is an ML project in order to automate ML processes
Home-page: https://github.com/overenginar/nexora
Author: Ali Cabukel
Keywords: xgboost,lightgbm,sklearn,optuna,shap
Requires-Python: <3.11,>=3.7
License-File: LICENSE
Requires-Dist: fastapi ==0.70.0
Requires-Dist: uvicorn ==0.15.0
Requires-Dist: optuna ==3.1.1
Requires-Dist: optuna-dashboard ==0.9.1
Requires-Dist: pyarrow ==12.0.0
Requires-Dist: pydantic ==1.8.2
Requires-Dist: joblib ==1.1.1
Requires-Dist: pandas ==1.3.4
Requires-Dist: numpy ==1.22
Requires-Dist: scikit-learn ==1.2.2
Requires-Dist: xgboost ==1.6.2
Requires-Dist: lightgbm ==4.3.0
Requires-Dist: shapash ==2.3.3
Provides-Extra: test
Requires-Dist: pytest ; extra == 'test'
Requires-Dist: coverage ; extra == 'test'
